main.py
mcp_calculate_server-1.0.0.dist-info/licenses/LICENSE
mcp_calculate_server-1.0.0.dist-info/METADATA
mcp_calculate_server-1.0.0.dist-info/WHEEL
mcp_calculate_server-1.0.0.dist-info/entry_points.txt
mcp_calculate_server-1.0.0.dist-info/top_level.txt
mcp_calculate_server-1.0.0.dist-info/RECORD
