Metadata-Version: 2.4
Name: mcp-calculate-server
Version: 1.0.0
Summary: 计算器MCP服务,输入字符串的计算式，返回计算结果,更新信息：添加幂运算支持，放宽计算结果小数位数限制，并增强了错误处理能力。
Requires-Python: >=3.10
License-File: LICENSE
Requires-Dist: mcp>=1.12.3
Dynamic: license-file
